shellrunner/__init__.py
shellrunner/_exceptions.py
shellrunner/_shellrunner.py
shellrunner/_utils.py
shellrunner/py.typed
python_shellrunner-0.3.5.dist-info/METADATA
python_shellrunner-0.3.5.dist-info/WHEEL
python_shellrunner-0.3.5.dist-info/licenses/LICENSE
python_shellrunner-0.3.5.dist-info/RECORD
