Metadata-Version: 2.1
Name: python-shellrunner
Version: 0.3.5
Summary: Write safe shell scripts in Python.
Project-URL: Homepage, https://github.com/adamhl8/python-shellrunner
Project-URL: Source, https://github.com/adamhl8/python-shellrunner
Project-URL: Bug Tracker, https://github.com/adamhl8/python-shellrunner/issues
Author-email: adamhl8 <adamhl@pm.me>
License: MIT
License-File: LICENSE
Keywords: bash,fish,scripting,shell,zsh
Classifier: Development Status :: 3 - Alpha
Classifier: License :: OSI Approved :: MIT License
Classifier: Operating System :: POSIX
Classifier: Operating System :: Unix
Classifier: Programming Language :: Python :: 3.10
Classifier: Programming Language :: Unix Shell
Classifier: Topic :: System :: Shells
Classifier: Topic :: System :: System Shells
Requires-Python: >=3.10
Requires-Dist: psutil>=5.9.5
